[{"trend": "Marketing & Strategy"},
{"trend": "The Customer in 2020"},
{"trend": "Agencies"},
{"trend": "B2B Commerce & Marketplaces"},
{"trend": "B2B Marketing & Sales"},
{"trend": "B2C Marketing"},
{"trend": "Banking"},
{"trend": "CMO"},
{"trend": "Customer Experience"},
{"trend": "Customer Insights"},
{"trend": "Employee Experience"},
{"trend": "Healthcare"},
{"trend": "Insurance"},
{"trend": "Media"},
{"trend": "Privacy & Data Ethics"},
{"trend": "Retail"},
{"trend": "Wealth Management"},
{"trend": "Technology Management"},
{"trend": "AI"},
{"trend": "Automation"},
{"trend": "CIO"},
{"trend": "Cloud"},
{"trend": "Customer Service"},
{"trend": "Cybersecurity"},
{"trend": "DevOps"},
{"trend": "Distributed Ledger Technology"},
{"trend": "Edge Computing"},
{"trend": "Europe"},
{"trend": "IoT"},
{"trend": "New Tech"},
{"trend": "Software Development"},
{"trend": "Predictions 2020: On The Precipice Of Far-Reaching Change      "},
{"trend": "\n    "}
]